CODE_OF_CONDUCT.md
LICENSE
MANIFEST.in
README.md
ez_setup.py
setup.py
uttr.py
uttrs.egg-info/PKG-INFO
uttrs.egg-info/SOURCES.txt
uttrs.egg-info/dependency_links.txt
uttrs.egg-info/requires.txt
uttrs.egg-info/top_level.txt