Metadata-Version: 2.1
Name: uttrs
Version: 0.4.1
Summary: 'uttrs' seeks to interoperate Classes definided using attrs and 'astropy units' in a simple manner.
Home-page: https://github.com/quatrope/utts
Author: JB Cabral and QuatroPe
Author-email: jbcabral@unc.edu.ar
License: 3 Clause BSD
Keywords: astronomy,oop,attrs,units,astropy
Platform: UNKNOWN
Classifier: Development Status :: 4 - Beta
Classifier: Intended Audience :: Education
Classifier: Intended Audience :: Science/Research
Classifier: License :: OSI Approved :: BSD License
Classifier: Operating System :: OS Independent
Classifier: Programming Language :: Python
Classifier: Programming Language :: Python :: 3.8
Classifier: Programming Language :: Python :: Implementation :: CPython
Classifier: Topic :: Scientific/Engineering
